django_model_to_excel/__init__.py
django_model_to_excel/generate_excel_file.py
django_model_to_excel-0.1.2.dist-info/LICENSE
django_model_to_excel-0.1.2.dist-info/METADATA
django_model_to_excel-0.1.2.dist-info/WHEEL
django_model_to_excel-0.1.2.dist-info/top_level.txt
django_model_to_excel-0.1.2.dist-info/RECORD
