Metadata-Version: 2.1
Name: django-model-to-excel
Version: 0.1.2
Summary: Simple Excel file Generator
Home-page: UNKNOWN
Author: H I Govinda
Author-email: higovind5@email.com
License: UNKNOWN
Platform: UNKNOWN
Classifier: Programming Language :: Python :: 3
Classifier: License :: OSI Approved :: MIT License
Classifier: Operating System :: OS Independent
Requires-Python: >=3.4
License-File: LICENSE
